temporalio/__init__.py
temporalio/activity.py
temporalio/api/__init__.py
temporalio/api/cluster/__init__.py
temporalio/api/cluster/v1/__init__.py
temporalio/api/cluster/v1/message_pb2.py
temporalio/api/cluster/v1/message_pb2.pyi
temporalio/api/cluster/v1/message_pb2_grpc.py
temporalio/api/cluster/v1/message_pb2_grpc.pyi
temporalio/api/command/__init__.py
temporalio/api/command/v1/__init__.py
temporalio/api/command/v1/message_pb2.py
temporalio/api/command/v1/message_pb2.pyi
temporalio/api/command/v1/message_pb2_grpc.py
temporalio/api/command/v1/message_pb2_grpc.pyi
temporalio/api/common/__init__.py
temporalio/api/common/v1/__init__.py
temporalio/api/common/v1/message_pb2.py
temporalio/api/common/v1/message_pb2.pyi
temporalio/api/common/v1/message_pb2_grpc.py
temporalio/api/common/v1/message_pb2_grpc.pyi
temporalio/api/dependencies/__init__.py
temporalio/api/dependencies/gogoproto/__init__.py
temporalio/api/dependencies/gogoproto/gogo_pb2.py
temporalio/api/dependencies/gogoproto/gogo_pb2.pyi
temporalio/api/dependencies/gogoproto/gogo_pb2_grpc.py
temporalio/api/dependencies/gogoproto/gogo_pb2_grpc.pyi
temporalio/api/enums/__init__.py
temporalio/api/enums/v1/__init__.py
temporalio/api/enums/v1/cluster_pb2.py
temporalio/api/enums/v1/cluster_pb2.pyi
temporalio/api/enums/v1/cluster_pb2_grpc.py
temporalio/api/enums/v1/cluster_pb2_grpc.pyi
temporalio/api/enums/v1/command_type_pb2.py
temporalio/api/enums/v1/command_type_pb2.pyi
temporalio/api/enums/v1/command_type_pb2_grpc.py
temporalio/api/enums/v1/command_type_pb2_grpc.pyi
temporalio/api/enums/v1/common_pb2.py
temporalio/api/enums/v1/common_pb2.pyi
temporalio/api/enums/v1/common_pb2_grpc.py
temporalio/api/enums/v1/common_pb2_grpc.pyi
temporalio/api/enums/v1/event_type_pb2.py
temporalio/api/enums/v1/event_type_pb2.pyi
temporalio/api/enums/v1/event_type_pb2_grpc.py
temporalio/api/enums/v1/event_type_pb2_grpc.pyi
temporalio/api/enums/v1/failed_cause_pb2.py
temporalio/api/enums/v1/failed_cause_pb2.pyi
village_temporalio-0.1b2.dist-info/LICENSE
village_temporalio-0.1b2.dist-info/WHEEL
village_temporalio-0.1b2.dist-info/METADATA
village_temporalio-0.1b2.dist-info/RECORD
