Metadata-Version: 2.1
Name: village-temporalio
Version: 0.1b2
Summary: Temporal.io Python SDK
Home-page: https://github.com/temporalio/sdk-python
License: MIT
Keywords: temporal,workflow
Author: Temporal Technologies Inc
Author-email: sdk@temporal.io
Requires-Python: >=3.7,<4.0
Classifier: License :: OSI Approved :: MIT License
Classifier: Programming Language :: Python :: 3
Classifier: Programming Language :: Python :: 3.10
Classifier: Programming Language :: Python :: 3.7
Classifier: Programming Language :: Python :: 3.8
Classifier: Programming Language :: Python :: 3.9
Provides-Extra: grpc
Provides-Extra: opentelemetry
Requires-Dist: grpcio (>=1.48.1,<2.0.0); extra == "grpc"
Requires-Dist: opentelemetry-api (>=1.11.1,<2.0.0); extra == "opentelemetry"
Requires-Dist: opentelemetry-sdk (>=1.11.1,<2.0.0); extra == "opentelemetry"
Requires-Dist: protobuf (>=4.21.5,<5.0.0)
Requires-Dist: types-protobuf (>=3.19.21,<4.0.0)
Requires-Dist: typing-extensions (>=4.2.0,<5.0.0)
Project-URL: Bug Tracker, https://github.com/temporalio/sdk-python/issues
Project-URL: Documentation, https://docs.temporal.io/docs/python
Project-URL: Repository, https://github.com/temporalio/sdk-python
